{
  "_id": "6641cae056a3b4897093b653",
  "source": "google",
  "url": "https://www.faz.net/aktuell/politik/inland/selbstbestimmungsgesetz-bundestag-stimmt-fuer-freie-geschlechtswahl-im-pass-19648984.html",
  "timestamp": "2026-02-06 13:44:24.364238",
  "content": "Als Sahra Wagenknecht das Rednerpult verlässt, wird es laut im Bundestag. Die Abgeordneten der Ampelfraktionen sind empört. Wagenknecht hatte gerade gegen das von der Regierung auf den Weg gebrachte Selbstbestimmungsgesetz polemisiert. „Einmal im Jahr sein Geschlecht frei wählen zu können, diesen grandiosen Freiheitsgewinn haben Millionen Bürgerinnen und Bürger sicher seit Jahren sehnlichst erwartet“, sagte Wagenknecht. Und wenig später: „Ihr Gesetz ist frauenfeindlich. Und Ihr Gesetz macht Eltern und Kinder zu Versuchskaninchen einer Ideologie, von der nur die Pharmalobby und die Pharmaindustrie profitieren. Das BSW sagt Nein zu diesem gefährlichen Irrsinn.“ SucheStartseiteDas Beste von FAZ+PORTAL Anhören Merken KommentareTeilenVerschenkenDruckenJardiman14.04.2024 – 13:58Wie Sie hier in den Kommentaren lesen können, unterscheidet sich die Haltung der \"Burkaträgerinnen\" nicht allzusehr von eingesessenen, erzkonsrvativ geprägten Nichtburkaträgern. Der Konflikt kann also keinesfalls Burkatragenden Migranten zugeschoben werden.991100Jardiman14.04.2024 – 11:30@Flo188 : Ich denke das Sie im Verteidigungsfall ganz andere Sorgen haben werden.221100Jardiman14.04.2024 – 11:11Leute sind besorgt ausgegrenzt zu werden ,weil sie andere nicht mehr ausgrenzen können ? Das ist eine interessante Sichtweise.662222ZurückVorVorschauGesünder kochenFinanz-ServicesWetterSpieleTV-ProgrammVeranstaltungenLogin / RegistrierenMerkzettel Einmal gespeichert, überall lesen oder hören Meine Themen Ihre Lieblingsthemen, immer im Blick Zuletzt gelesen Ihre gelesenen Beiträge im Suche Suche  Startseite  FAZ+ Das Beste von FAZ+  PolitikÖffnen  Sicherheitskonferenz  USA unter Trump  Ukraine  Inland  Ausland  Politische Bücher  PRO Einspruch  Geschichte  Briefe an die Herausgeber  WirtschaftÖffnen  Was kostet die Welt?  Unternehmen  Immobilien & Wohnen  Auto & Verkehr  Klima & Nachhaltigkeit  PRO Digitalwirtschaft  PRO Weltwirtschaft  Arm und reich  Schneller schlau  Wirtschaftswissen  FinanzenÖffnen  PRO Finanzen  Finanzmarkt  Börsen & Märkte  Mein Depot  Börsenlexikon  FeuilletonÖffnen  Debatten  Bücher  Medien und Film  Musik und Bühne  Kunst und Architektur  Kunstmarkt  Kolumnen  TV-Programm  KarriereÖffnen  Büro & Co  Hörsaal  Klassenzimmer  Die Karrierefrage  SportÖffnen  Olympische Winterspiele  Fußball  Formel 1  Mehr Sport  Rhein-Main-Sport  Sportpolitik  Wintersport  Sport-Tipps  Sport Live  Sport-Ergebnisse  GesellschaftÖffnen  Menschen  Kriminalität  Unglücke  Gesundheit  Tiere  Smalltalk  Jugend schreibt  StilÖffnen  Essen & Trinken  Mode & Design  Leib & Seele  Eltern & Familie  Trends & Nischen  Rhein-MainÖffnen  Frankfurt  Region und Hessen  Wirtschaft  Sport  Kultur  F.A.Z. Leser helfen  Veranstaltungen  Technik und MotorÖffnen  Motor  Elektromobilität  Technik  Digital  Energie  WissenÖffnen  Medizin & Ernährung  Krebsmedizin  Forschung & Politik  Weltraum  Leben & Gene  Erde & Klima  Physik & Mehr  Archäologie & Altertum  Geist & Soziales  Ab in die Botanik  Netzrätsel  ReiseÖffnen  Wetter Zeitung Edition Sonntagszeitung Edition Zeitung E-Paper Sonntagszeitung E-Paper FAZ Quarterly FAZ Magazin FAZ Metropol F.A.Z. Der Tag App F.A.Z. Kiosk App F.A.Z. PRO Digitalwirtschaft F.A.Z. PRO Weltwirtschaft F.A.Z. PRO Einspruch F.A.Z. PRO Finanzen  Gesünder kochen  Daten & Visualisierung  Fotografie  Newsletter  Podcasts  Agenturmeldungen Suche Suche  Startseite  FAZ+ Das Beste von FAZ+  PolitikÖffnen  Sicherheitskonferenz  USA unter Trump  Ukraine  Inland  Ausland  Politische Bücher  PRO Einspruch  Geschichte  Briefe an die Herausgeber  WirtschaftÖffnen  Was kostet die Welt?  Unternehmen  Immobilien & Wohnen  Auto & Verkehr  Klima & Nachhaltigkeit  PRO Digitalwirtschaft  PRO Weltwirtschaft  Arm und reich  Schneller schlau  Wirtschaftswissen  FinanzenÖffnen  PRO Finanzen  Finanzmarkt  Börsen & Märkte  Mein Depot  Börsenlexikon  FeuilletonÖffnen  Debatten  Bücher  Medien und Film  Musik und Bühne  Kunst und Architektur  Kunstmarkt  Kolumnen  TV-Programm  KarriereÖffnen  Büro & Co  Hörsaal  Klassenzimmer  Die Karrierefrage  SportÖffnen  Olympische Winterspiele  Fußball  Formel 1  Mehr Sport  Rhein-Main-Sport  Sportpolitik  Wintersport  Sport-Tipps  Sport Live  Sport-Ergebnisse  GesellschaftÖffnen  Menschen  Kriminalität  Unglücke  Gesundheit  Tiere  Smalltalk  Jugend schreibt  StilÖffnen  Essen & Trinken  Mode & Design  Leib & Seele  Eltern & Familie  Trends & Nischen  Rhein-MainÖffnen  Frankfurt  Region und Hessen  Wirtschaft  Sport  Kultur  F.A.Z. Leser helfen  Veranstaltungen  Technik und MotorÖffnen  Motor  Elektromobilität  Technik  Digital  Energie  WissenÖffnen  Medizin & Ernährung  Krebsmedizin  Forschung & Politik  Weltraum  Leben & Gene  Erde & Klima  Physik & Mehr  Archäologie & Altertum  Geist & Soziales  Ab in die Botanik  Netzrätsel  ReiseÖffnen  Wetter Zeitung Edition Sonntagszeitung Edition Zeitung E-Paper Sonntagszeitung E-Paper FAZ Quarterly FAZ Magazin FAZ Metropol F.A.Z. Der Tag App F.A.Z. Kiosk App F.A.Z. PRO Digitalwirtschaft F.A.Z. PRO Weltwirtschaft F.A.Z. PRO Einspruch F.A.Z. PRO Finanzen  Gesünder kochen  Daten & Visualisierung  Fotografie  Newsletter  Podcasts  Agenturmeldungen Suche Suche  Startseite  FAZ+ Das Beste von FAZ+  PolitikÖffnen  Sicherheitskonferenz  USA unter Trump  Ukraine  Inland  Ausland  Politische Bücher  PRO Einspruch  Geschichte  Briefe an die Herausgeber  WirtschaftÖffnen  Was kostet die Welt?  Unternehmen  Immobilien & Wohnen  Auto & Verkehr  Klima & Nachhaltigkeit  PRO Digitalwirtschaft  PRO Weltwirtschaft  Arm und reich  Schneller schlau  Wirtschaftswissen  FinanzenÖffnen  PRO Finanzen  Finanzmarkt  Börsen & Märkte  Mein Depot  Börsenlexikon  FeuilletonÖffnen  Debatten  Bücher  Medien und Film  Musik und Bühne  Kunst und Architektur  Kunstmarkt  Kolumnen  TV-Programm  KarriereÖffnen  Büro & Co  Hörsaal  Klassenzimmer  Die Karrierefrage  SportÖffnen  Olympische Winterspiele  Fußball  Formel 1  Mehr Sport  Rhein-Main-Sport  Sportpolitik  Wintersport  Sport-Tipps  Sport Live  Sport-Ergebnisse  GesellschaftÖffnen  Menschen  Kriminalität  Unglücke  Gesundheit  Tiere  Smalltalk  Jugend schreibt  StilÖffnen  Essen & Trinken  Mode & Design  Leib & Seele  Eltern & Familie  Trends & Nischen  Rhein-MainÖffnen  Frankfurt  Region und Hessen  Wirtschaft  Sport  Kultur  F.A.Z. Leser helfen  Veranstaltungen  Technik und MotorÖffnen  Motor  Elektromobilität  Technik  Digital  Energie  WissenÖffnen  Medizin & Ernährung  Krebsmedizin  Forschung & Politik  Weltraum  Leben & Gene  Erde & Klima  Physik & Mehr  Archäologie & Altertum  Geist & Soziales  Ab in die Botanik  Netzrätsel  ReiseÖffnen  Wetter Zeitung Edition Sonntagszeitung Edition Zeitung E-Paper Sonntagszeitung E-Paper FAZ Quarterly FAZ Magazin FAZ Metropol F.A.Z. Der Tag App F.A.Z. Kiosk App F.A.Z. PRO Digitalwirtschaft F.A.Z. PRO Weltwirtschaft F.A.Z. PRO Einspruch F.A.Z. PRO Finanzen  Gesünder kochen  Daten & Visualisierung  Fotografie  Newsletter  Podcasts  Agenturmeldungen Suche Suche PolitikÖffnen WirtschaftÖffnen FinanzenÖffnen FeuilletonÖffnen KarriereÖffnen SportÖffnen GesellschaftÖffnen Rhein-MainÖffnen Technik und MotorÖffnen WissenÖffnen ReiseÖffnen Zeitung Edition Sonntagszeitung Edition Zeitung E-Paper Sonntagszeitung E-Paper FAZ Quarterly FAZ Magazin FAZ Metropol F.A.Z. Der Tag App F.A.Z. Kiosk App F.A.Z. PRO Digitalwirtschaft F.A.Z. PRO Weltwirtschaft F.A.Z. PRO Einspruch F.A.Z. PRO Finanzen Zeitung Edition Zeitung Edition Sonntagszeitung Edition Sonntagszeitung Edition Zeitung E-Paper Zeitung E-Paper Sonntagszeitung E-Paper Sonntagszeitung E-Paper FAZ Quarterly FAZ Magazin FAZ Metropol F.A.Z. Der Tag App F.A.Z. Kiosk App F.A.Z. PRO Digitalwirtschaft F.A.Z. PRO Weltwirtschaft F.A.Z. PRO Einspruch F.A.Z. PRO Finanzen F.A.Z. Der Tag App F.A.Z. Kiosk App F.A.Z. PRO Digitalwirtschaft F.A.Z. PRO Weltwirtschaft F.A.Z. PRO Einspruch F.A.Z. PRO Finanzen Gesünder kochen Daten & Visualisierung Agenturmeldungen Direkt zum Hauptinhalt ",
  "web_title": "Bundestag stimmt für freie Geschlechtswahl im Pass",
  "query": "ist das geschlecht wählbar",
  "query_type": "gender",
  "country": "de",
  "themes": "['IDEOLOGY', 'AFFECT', 'KILL', 'CONSTITUTIONAL', 'MEDICAL', 'ARREST']",
  "tone": -3.55677154582763,
  "success": true
}